mkdocstrings_handlers/zig/__init__.py
mkdocstrings_handlers/zig/_internal/__init__.py
mkdocstrings_handlers/zig/_internal/config.py
mkdocstrings_handlers/zig/_internal/debug.py
mkdocstrings_handlers/zig/_internal/handler.py
mkdocstrings_handlers/zig/_internal/zig_docs_extractor.py
mkdocstrings_handlers/zig/py.typed
mkdocstrings_handlers/zig/templates/material/_base/constant.html.jinja
mkdocstrings_handlers/zig/templates/material/_base/docstring.html.jinja
mkdocstrings_handlers/zig/templates/material/_base/fields.html.jinja
mkdocstrings_handlers/zig/templates/material/_base/function.html.jinja
mkdocstrings_handlers/zig/templates/material/_base/heading.html.jinja
mkdocstrings_handlers/zig/templates/material/_base/module.html.jinja
mkdocstrings_handlers/zig/templates/material/_base/parameters.html.jinja
mkdocstrings_handlers/zig/templates/material/_base/root.html.jinja
mkdocstrings_handlers/zig/templates/material/_base/struct.html.jinja
mkdocstrings_handlers/zig/templates/material/constant.html.jinja
mkdocstrings_handlers/zig/templates/material/docstring.html.jinja
mkdocstrings_handlers/zig/templates/material/fields.html.jinja
mkdocstrings_handlers/zig/templates/material/function.html.jinja
mkdocstrings_handlers/zig/templates/material/heading.html.jinja
mkdocstrings_handlers/zig/templates/material/module.html.jinja
mkdocstrings_handlers/zig/templates/material/parameters.html.jinja
mkdocstrings_handlers/zig/templates/material/root.html.jinja
mkdocstrings_handlers/zig/templates/material/struct.html.jinja
mkdocstrings_handlers/zig/templates/material/style.css
mkdocstrings_zig-0.0.7.dist-info/METADATA
mkdocstrings_zig-0.0.7.dist-info/WHEEL
mkdocstrings_zig-0.0.7.dist-info/entry_points.txt
mkdocstrings_zig-0.0.7.dist-info/licenses/LICENSE
mkdocstrings_zig-0.0.7.dist-info/RECORD
