Metadata-Version: 2.4
Name: mkdocstrings-zig
Version: 0.0.7
Summary: A Zig handler for mkdocstrings.
Author-Email: insolor <insolor@gmail.com>
License-Expression: ISC
License-File: LICENSE
Classifier: Development Status :: 4 - Beta
Classifier: Intended Audience :: Developers
Classifier: Programming Language :: Python
Classifier: Programming Language :: Python :: 3
Classifier: Programming Language :: Python :: 3 :: Only
Classifier: Programming Language :: Python :: 3.10
Classifier: Programming Language :: Python :: 3.11
Classifier: Programming Language :: Python :: 3.12
Classifier: Programming Language :: Python :: 3.13
Classifier: Topic :: Documentation
Classifier: Topic :: Software Development
Classifier: Topic :: Utilities
Classifier: Typing :: Typed
Project-URL: Documentation, https://insolor.github.io/mkdocstrings-zig
Project-URL: Repository, https://github.com/insolor/mkdocstrings-zig
Project-URL: Issues, https://github.com/insolor/mkdocstrings-zig/issues
Project-URL: Discussions, https://github.com/insolor/mkdocstrings-zig/discussions
Requires-Python: >=3.10
Requires-Dist: mkdocstrings>=0.18
Requires-Dist: tree-sitter>=0.25.0
Requires-Dist: tree-sitter-zig>=1.1.2
